{
  "$schema": "../../jigsaw/jigsawCampaignFramework.json",
  "locations": [
    {
      "locationName": "(F)lying  Michael",
      "locationEnum": "F",
      "startingGateFile": "src/worlds/LostBoys/MichaelFlying.json",
      "extraFiles": []
    }
  ],
  "goals": [
    {
      "goalName": "get the keys",
      "goalEnum": "G1",
      "location": "F",
      "prerequisiteGoals": [],
      "prerequisiteType": "zeroConditions",
      "sunsetGoals": [],
      "sunsetType": "zeroConditions"
    }
  ]
}
